doxystub/__init__.py
doxystub/doxygen_parse.py
doxystub/doxystub.py
doxystub-0.0.13.dist-info/METADATA
doxystub-0.0.13.dist-info/WHEEL
doxystub-0.0.13.dist-info/entry_points.txt
doxystub-0.0.13.dist-info/top_level.txt
doxystub-0.0.13.dist-info/RECORD
