Metadata-Version: 2.1
Name: doxystub
Version: 0.0.13
Summary: Stubs generator based on Doxygen+Boost.Python
Home-page: https://github.com/rhoban/doxystub
Maintainer: Grégoire Passault
Maintainer-email: g.passault@gmail.com
License: MIT
Platform: UNKNOWN
